alerta_slack.py
setup.py
alerta_slack.egg-info/PKG-INFO
alerta_slack.egg-info/SOURCES.txt
alerta_slack.egg-info/dependency_links.txt
alerta_slack.egg-info/entry_points.txt
alerta_slack.egg-info/requires.txt
alerta_slack.egg-info/top_level.txt
alerta_slack.egg-info/zip-safe