Metadata-Version: 1.0
Name: alerta-slack
Version: 0.3.3
Summary: Alerta plugin for Slack
Home-page: https://github.com/alerta/alerta-contrib
Author: Nick Satterly
Author-email: nick.satterly@theguardian.com
License: MIT
Platform: UNKNOWN
